Workbook
Name customers: customer[#All]

Sheet Sheet2
A3: Row Labels | B3: Sum of Revenue | C3: Sum of profit | E3: Row Labels | F3: Sum of Revenue
A4: May | B4: 9952204 | C4: -717081 | E4: South | F4: 27299096
A5: Mar | B5: 9448223 | C5: -2027670 | E5: East | F5: 25825804
A6: Aug | B6: 9122764 | C6: -828716 | E6: West | F6: 24902740
A7: Jan | B7: 9082515 | C7: -1028892 | E7: North | F7: 24518864
A8: Dec | B8: 8824628 | C8: -646468 | E8: Grand Total | F8: 102546504
A9: Feb | B9: 8795167 | C9: -890226
A10: Nov | B10: 8438851 | C10: -2204371
A11: Apr | B11: 8284518 | C11: -1653288
A12: Sep | B12: 8181210 | C12: -1398139
A13: Oct | B13: 7690421 | C13: -832101
A14: Jun | B14: 7483431 | C14: -572144
A15: Jul | B15: 7242572 | C15: -1190417
A16: Grand Total | B16: 102546504 | C16: -13989513

Sheet orders
A1: order_id | B1: order_date | C1: customer_id | D1: Customer_name | E1: product_id | F1: quantity | G1: selling_price | H1: discount | I1: region | J1: order_status | K1: City | L1: State | M1: product_name | N1: category | O1: cost_price | P1: ship_date | Q1: delivery_date | R1: courier | S1: profit | T1: Revenue
A2: 1 | B2: 45373 | C2: 160 | D2: =_xlfn.XLOOKUP(order[[#This Row],[customer_id]],customer[customer_id],customer[customer_name]) -> Arjun Nair | E2: 207 | F2: 2 | G2: 58397 | H2: 2079 | I2: South | J2: Cancelled | K2: =_xlfn.XLOOKUP(order[[#This Row],[customer_id]],customer[customer_id],customer[city]) -> Delhi | L2: =_xlfn.XLOOKUP(order[[#This Row],[customer_id]],customer[customer_id],customer[state]) -> Delhi | M2: =_xlfn.XLOOKUP(order[[#This Row],[product_id]],products!$A$2:$A$11,products!$B$2:$B$11) -> Sony WH-1000XM4 Headphones | N2: =_xlfn.XLOOKUP(order[[#This Row],[product_id]],products!$A$2:$A$11,products!$C$2:$C$11) -> Electronics | O2: =_xlfn.XLOOKUP(order[[#This Row],[product_id]],Table4[product_id],Table4[cost_price]) -> 20000 | P2: =_xlfn.XLOOKUP(order[[#This Row],[order_id]],shipment[order_id],shipment[ship_date]) -> 45598 | Q2: =_xlfn.XLOOKUP(order[[#This Row],[order_id]],shipment[order_id],shipment[delivery_date]) -> 45599 | R2: =_xlfn.XLOOKUP(order[[#This Row],[order_id]],shipment[shipment_id],shipment[courier]) -> BlueDart | S2: =order[[#This Row],[selling_price]]-order[[#This Row],[cost_price]]*order[[#This Row],[quantity]]-order[[#This Row],[discount]] -> 16318 | T2: =order[[#This Row],[quantity]]*order[[#This Row],[selling_price]] -> 116794
A3: 304 | B3: 45295 | C3: 237 | D3: =_xlfn.XLOOKUP(order[[#This Row],[customer_id]],customer[customer_id],customer[customer_name]) -> Ananya Gupta | E3: 201 | F3: 2 | G3: 16842 | H3: 4990 | I3: West | J3: Pending | K3: =_xlfn.XLOOKUP(order[[#This Row],[customer_id]],customer[customer_id],customer[city]) -> Hyderabad | L3: =_xlfn.XLOOKUP(order[[#This Row],[customer_id]],customer[customer_id],customer[state]) -> Telangana | M3: =_xlfn.XLOOKUP(order[[#This Row],[product_id]],products!$A$2:$A$11,products!$B$2:$B$11) -> iPhone 13 | N3: =_xlfn.XLOOKUP(order[[#This Row],[product_id]],products!$A$2:$A$11,products!$C$2:$C$11) -> Electronics | O3: =_xlfn.XLOOKUP(order[[#This Row],[product_id]],Table4[product_id],Table4[cost_price]) -> 52000 | P3: =_xlfn.XLOOKUP(order[[#This Row],[order_id]],shipment[order_id],shipment[ship_date]) -> 45358 | Q3: =_xlfn.XLOOKUP(order[[#This Row],[order_id]],shipment[order_id],shipment[delivery_date]) -> 45364 | R3: =_xlfn.XLOOKUP(order[[#This Row],[order_id]],shipment[shipment_id],shipment[courier]) -> BlueDart | S3: =order[[#This Row],[selling_price]]-order[[#This Row],[cost_price]]*order[[#This Row],[quantity]]-order[[#This Row],[discount]] -> -92148 | T3: =order[[#This Row],[quantity]]*order[[#This Row],[selling_price]] -> 33684
A4: 586 | B4: 45546 | C4: 211 | D4: =_xlfn.XLOOKUP(order[[#This Row],[customer_id]],customer[customer_id],customer[customer_name]) -> Aarav Sharma | E4: 201 | F4: 2 | G4: 37043 | H4: 4981 | I4: East | J4: Cancelled | K4: =_xlfn.XLOOKUP(order[[#This Row],[customer_id]],customer[customer_id],customer[city]) -> Ahmedabad | L4: =_xlfn.XLOOKUP(order[[#This Row],[customer_id]],customer[customer_id],customer[state]) -> Gujarat | M4: =_xlfn.XLOOKUP(order[[#This Row],[product_id]],products!$A$2:$A$11,products!$B$2:$B$11) -> iPhone 13 | N4: =_xlfn.XLOOKUP(order[[#This Row],[product_id]],products!$A$2:$A$11,products!$C$2:$C$11) -> Electronics | O4: =_xlfn.XLOOKUP(order[[#This Row],[product_id]],Table4[product_id],Table4[cost_price]) -> 52000 | P4: =_xlfn.XLOOKUP(order[[#This Row],[order_id]],shipment[order_id],shipment[ship_date]) -> 45637 | Q4: =_xlfn.XLOOKUP(order[[#This Row],[order_id]],shipment[order_id],shipment[delivery_date]) -> 45642 | R4: =_xlfn.XLOOKUP(order[[#This Row],[order_id]],shipment[shipment_id],shipment[courier]) -> Ekart | S4: =order[[#This Row],[selling_price]]-order[[#This Row],[cost_price]]*order[[#This Row],[quantity]]-order[[#This Row],[discount]] -> -71938 | T4: =order[[#This Row],[quantity]]*order[[#This Row],[selling_price]] -> 74086
A5: 4 | B5: 45357 | C5: 163 | D5: =_xlfn.XLOOKUP(order[[#This Row],[customer_id]],customer[customer_id],customer[customer_name]) -> Ananya Gupta | E5: 204 | F5: 2 | G5: 56025 | H5: 3451 | I5: West | J5: Cancelled | K5: =_xlfn.XLOOKUP(order[[#This Row],[customer_id]],customer[customer_id],customer[city]) -> Chennai | L5: =_xlfn.XLOOKUP(order[[#This Row],[customer_id]],customer[customer_id],customer[state]) -> Tamil Nadu | M5: =_xlfn.XLOOKUP(order[[#This Row],[product_id]],products!$A$2:$A$11,products!$B$2:$B$11) -> Levi's Slim Fit Jeans | N5: =_xlfn.XLOOKUP(order[[#This Row],[product_id]],products!$A$2:$A$11,products!$C$2:$C$11) -> Fashion | O5: =_xlfn.XLOOKUP(order[[#This Row],[product_id]],Table4[product_id],Table4[cost_price]) -> 1800 | P5: =_xlfn.XLOOKUP(order[[#This Row],[order_id]],shipment[order_id],shipment[ship_date]) -> 45657 | Q5: =_xlfn.XLOOKUP(order[[#This Row],[order_id]],shipment[order_id],shipment[delivery_date]) -> 45661 | R5: =_xlfn.XLOOKUP(order[[#This Row],[order_id]],shipment[shipment_id],shipment[courier]) -> Delhivery | S5: =order[[#This Row],[selling_price]]-order[[#This Row],[cost_price]]*order[[#This Row],[quantity]]-order[[#This Row],[discount]] -> 48974 | T5: =order[[#This Row],[quantity]]*order[[#This Row],[selling_price]] -> 112050
A6: 5 | B6: 45412 | C6: 257 | D6: =_xlfn.XLOOKUP(order[[#This Row],[customer_id]],customer[customer_id],customer[customer_name]) -> Siddharth Jain | E6: 206 | F6: 1 | G6: 58741 | H6: 2418 | I6: West | J6: Pending | K6: =_xlfn.XLOOKUP(order[[#This Row],[customer_id]],customer[customer_id],customer[city]) -> Pune | L6: =_xlfn.XLOOKUP(order[[#This Row],[customer_id]],customer[customer_id],customer[state]) -> Maharashtra | M6: =_xlfn.XLOOKUP(order[[#This Row],[product_id]],products!$A$2:$A$11,products!$B$2:$B$11) -> Philips Air Fryer | N6: =_xlfn.XLOOKUP(order[[#This Row],[product_id]],products!$A$2:$A$11,products!$C$2:$C$11) -> Home & Kitchen | O6: =_xlfn.XLOOKUP(order[[#This Row],[product_id]],Table4[product_id],Table4[cost_price]) -> 7000 | P6: =_xlfn.XLOOKUP(order[[#This Row],[order_id]],shipment[order_id],shipment[ship_date]) -> 45407 | Q6: =_xlfn.XLOOKUP(order[[#This Row],[order_id]],shipment[order_id],shipment[delivery_date]) -> 45412 | R6: =_xlfn.XLOOKUP(order[[#This Row],[order_id]],shipment[shipment_id],shipment[courier]) -> Ekart | S6: =order[[#This Row],[selling_price]]-order[[#This Row],[cost_price]]*order[[#This Row],[quantity]]-order[[#This Row],[discount]] -> 49323 | T6: =order[[#This Row],[quantity]]*order[[#This Row],[selling_price]] -> 58741
A7: 6 | B7: 45449 | C7: 286 | D7: =_xlfn.XLOOKUP(order[[#This Row],[customer_id]],customer[customer_id],customer[customer_name]) -> Arjun Nair | E7: 206 | F7: 1 | G7: 22097 | H7: 2668 | I7: North | J7: Cancelled | K7: =_xlfn.XLOOKUP(order[[#This Row],[customer_id]],customer[customer_id],customer[city]) -> Hyderabad | L7: =_xlfn.XLOOKUP(order[[#This Row],[customer_id]],customer[customer_id],customer[state]) -> Telangana | M7: =_xlfn.XLOOKUP(order[[#This Row],[product_id]],products!$A$2:$A$11,products!$B$2:$B$11) -> Philips Air Fryer | N7: =_xlfn.XLOOKUP(order[[#This Row],[product_id]],products!$A$2:$A$11,products!$C$2:$C$11) -> Home & Kitchen | O7: =_xlfn.XLOOKUP(order[[#This Row],[product_id]],Table4[product_id],Table4[cost_price]) -> 7000 | P7: =_xlfn.XLOOKUP(order[[#This Row],[order_id]],shipment[order_id],shipment[ship_date]) -> 45609 | Q7: =_xlfn.XLOOKUP(order[[#This Row],[order_id]],shipment[order_id],shipment[delivery_date]) -> 45613 | R7: =_xlfn.XLOOKUP(order[[#This Row],[order_id]],shipment[shipment_id],shipment[courier]) -> Ekart | S7: =order[[#This Row],[selling_price]]-order[[#This Row],[cost_price]]*order[[#This Row],[quantity]]-order[[#This Row],[discount]] -> 12429 | T7: =order[[#This Row],[quantity]]*order[[#This Row],[selling_price]] -> 22097
A8: 7 | B8: 45421 | C8: 145 | D8: =_xlfn.XLOOKUP(order[[#This Row],[customer_id]],customer[customer_id],customer[customer_name]) -> Meera Joshi | E8: 204 | F8: 3 | G8: 63189 | H8: 4594 | I8: West | J8: Delivered | K8: =_xlfn.XLOOKUP(order[[#This Row],[customer_id]],customer[customer_id],customer[city]) -> Ahmedabad | L8: =_xlfn.XLOOKUP(order[[#This Row],[customer_id]],customer[customer_id],customer[state]) -> Gujarat | M8: =_xlfn.XLOOKUP(order[[#This Row],[product_id]],products!$A$2:$A$11,products!$B$2:$B$11) -> Levi's Slim Fit Jeans | N8: =_xlfn.XLOOKUP(order[[#This Row],[product_id]],products!$A$2:$A$11,products!$C$2:$C$11) -> Fashion | O8: =_xlfn.XLOOKUP(order[[#This Row],[product_id]],Table4[product_id],Table4[cost_price]) -> 1800 | P8: =_xlfn.XLOOKUP(order[[#This Row],[order_id]],shipment[order_id],shipment[ship_date]) -> 45637 | Q8: =_xlfn.XLOOKUP(order[[#This Row],[order_id]],shipment[order_id],shipment[delivery_date]) -> 45647 | R8: =_xlfn.XLOOKUP(order[[#This Row],[order_id]],shipment[shipment_id],shipment[courier]) -> BlueDart | S8: =order[[#This Row],[selling_price]]-order[[#This Row],[cost_price]]*order[[#This Row],[quantity]]-order[[#This Row],[discount]] -> 53195 | T8: =order[[#This Row],[quantity]]*order[[#This Row],[selling_price]] -> 189567
A9: 1047 | B9: 45545 | C9: 139 | D9: =_xlfn.XLOOKUP(order[[#This Row],[customer_id]],customer[customer_id],customer[customer_name]) -> Neha Kapoor | E9: 201 | F9: 2 | G9: 10882 | H9: 4848 | I9: South | J9: Delivered | K9: =_xlfn.XLOOKUP(order[[#This Row],[customer_id]],customer[customer_id],customer[city]) -> Chennai | L9: =_xlfn.XLOOKUP(order[[#This Row],[customer_id]],customer[customer_id],customer[state]) -> Tamil Nadu | M9: =_xlfn.XLOOKUP(order[[#This Row],[product_id]],products!$A$2:$A$11,products!$B$2:$B$11) -> iPhone 13 | N9: =_xlfn.XLOOKUP(order[[#This Row],[product_id]],products!$A$2:$A$11,products!$C$2:$C$11) -> Electronics | O9: =_xlfn.XLOOKUP(order[[#This Row],[product_id]],Table4[product_id],Table4[cost_price]) -> 52000 | P9: =_xlfn.XLOOKUP(order[[#This Row],[order_id]],shipment[order_id],shipment[ship_date]) -> 45608 | Q9: =_xlfn.XLOOKUP(order[[#This Row],[order_id]],shipment[order_id],shipment[delivery_date]) -> 45609 | R9: =_xlfn.XLOOKUP(order[[#This Row],[order_id]],shipment[shipment_id],shipment[courier]) -> Delhivery | S9: =order[[#This Row],[selling_price]]-order[[#This Row],[cost_price]]*order[[#This Row],[quantity]]-order[[#This Row],[discount]] -> -97966 | T9: =order[[#This Row],[quantity]]*order[[#This Row],[selling_price]] -> 21764
A10: 772 | B10: 45453 | C10: 108 | D10: =_xlfn.XLOOKUP(order[[#This Row],[customer_id]],customer[customer_id],customer[customer_name]) -> Arjun Nair | E10: 201 | F10: 4 | G10: 13039 | H10: 4846 | I10: East | J10: Pending | K10: =_xlfn.XLOOKUP(order[[#This Row],[customer_id]],customer[customer_id],customer[city]) -> Ahmedabad | L10: =_xlfn.XLOOKUP(order[[#This Row],[customer_id]],customer[customer_id],customer[state]) -> Gujarat | M10: =_xlfn.XLOOKUP(order[[#This Row],[product_id]],products!$A$2:$A$11,products!$B$2:$B$11) -> iPhone 13 | N10: =_xlfn.XLOOKUP(order[[#This Row],[product_id]],products!$A$2:$A$11,products!$C$2:$C$11) -> Electronics | O10: =_xlfn.XLOOKUP(order[[#This Row],[product_id]],Table4[product_id],Table4[cost_price]) -> 52000 | P10: =_xlfn.XLOOKUP(order[[#This Row],[order_id]],shipment[order_id],shipment[ship_date]) -> 45472 | Q10: =_xlfn.XLOOKUP(order[[#This Row],[order_id]],shipment[order_id],shipment[delivery_date]) -> 45474 | R10: =_xlfn.XLOOKUP(order[[#This Row],[order_id]],shipment[shipment_id],shipment[courier]) -> Delhivery | S10: =order[[#This Row],[selling_price]]-order[[#This Row],[cost_price]]*order[[#This Row],[quantity]]-order[[#This Row],[discount]] -> -199807 | T10: =order[[#This Row],[quantity]]*order[[#This Row],[selling_price]] -> 52156
A11: 570 | B11: 45576 | C11: 205 | D11: =_xlfn.XLOOKUP(order[[#This Row],[customer_id]],customer[customer_id],customer[customer_name]) -> Siddharth Jain | E11: 201 | F11: 1 | G11: 46635 | H11: 4738 | I11: North | J11: Cancelled | K11: =_xlfn.XLOOKUP(order[[#This Row],[customer_id]],customer[customer_id],customer[city]) -> Hyderabad | L11: =_xlfn.XLOOKUP(order[[#This Row],[customer_id]],customer[customer_id],customer[state]) -> Telangana | M11: =_xlfn.XLOOKUP(order[[#This Row],[product_id]],products!$A$2:$A$11,products!$B$2:$B$11) -> iPhone 13 | N11: =_xlfn.XLOOKUP(order[[#This Row],[product_id]],products!$A$2:$A$11,products!$C$2:$C$11) -> Electronics | O11: =_xlfn.XLOOKUP(order[[#This Row],[product_id]],Table4[product_id],Table4[cost_price]) -> 52000 | P11: =_xlfn.XLOOKUP(order[[#This Row],[order_id]],shipment[order_id],shipment[ship_date]) -> 45615 | Q11: =_xlfn.XLOOKUP(order[[#This Row],[order_id]],shipment[order_id],shipment[delivery_date]) -> 45625 | R11: =_xlfn.XLOOKUP(order[[#This Row],[order_id]],shipment[shipment_id],shipment[courier]) -> Delhivery | S11: =order[[#This Row],[selling_price]]-order[[#This Row],[cost_price]]*order[[#This Row],[quantity]]-order[[#This Row],[discount]] -> -10103 | T11: =order[[#This Row],[quantity]]*order[[#This Row],[selling_price]] -> 46635
A12: 11 | B12: 45526 | C12: 102 | D12: =_xlfn.XLOOKUP(order[[#This Row],[customer_id]],customer[customer_id],customer[customer_name]) -> Aarav Sharma | E12: 204 | F12: 2 | G12: 32731 | H12: 1640 | I12: South | J12: Pending | K12: =_xlfn.XLOOKUP(order[[#This Row],[customer_id]],customer[customer_id],customer[city]) -> Delhi | L12: =_xlfn.XLOOKUP(order[[#This Row],[customer_id]],customer[customer_id],customer[state]) -> Delhi | M12: =_xlfn.XLOOKUP(order[[#This Row],[product_id]],products!$A$2:$A$11,products!$B$2:$B$11) -> Levi's Slim Fit Jeans | N12: =_xlfn.XLOOKUP(order[[#This Row],[product_id]],products!$A$2:$A$11,products!$C$2:$C$11) -> Fashion | O12: =_xlfn.XLOOKUP(order[[#This Row],[product_id]],Table4[product_id],Table4[cost_price]) -> 1800 | P12: =_xlfn.XLOOKUP(order[[#This Row],[order_id]],shipment[order_id],shipment[ship_date]) -> 45345 | Q12: =_xlfn.XLOOKUP(order[[#This Row],[order_id]],shipment[order_id],shipment[delivery_date]) -> 45347 | R12: =_xlfn.XLOOKUP(order[[#This Row],[order_id]],shipment[shipment_id],shipment[courier]) -> Delhivery | S12: =order[[#This Row],[selling_price]]-order[[#This Row],[cost_price]]*order[[#This Row],[quantity]]-order[[#This Row],[discount]] -> 27491 | T12: =order[[#This Row],[quantity]]*order[[#This Row],[selling_price]] -> 65462
A13: 114 | B13: 45516 | C13: 264 | D13: =_xlfn.XLOOKUP(order[[#This Row],[customer_id]],customer[customer_id],customer[customer_name]) -> Ishita Bose | E13: 201 | F13: 2 | G13: 17340 | H13: 4582 | I13: North | J13: Delivered | K13: =_xlfn.XLOOKUP(order[[#This Row],[customer_id]],customer[customer_id],customer[city]) -> Delhi | L13: =_xlfn.XLOOKUP(order[[#This Row],[customer_id]],customer[customer_id],customer[state]) -> Delhi | M13: =_xlfn.XLOOKUP(order[[#This Row],[product_id]],products!$A$2:$A$11,products!$B$2:$B$11) -> iPhone 13 | N13: =_xlfn.XLOOKUP(order[[#This Row],[product_id]],products!$A$2:$A$11,products!$C$2:$C$11) -> Electronics | O13: =_xlfn.XLOOKUP(order[[#This Row],[product_id]],Table4[product_id],Table4[cost_price]) -> 52000 | P13: =_xlfn.XLOOKUP(order[[#This Row],[order_id]],shipment[order_id],shipment[ship_date]) -> 45565 | Q13: =_xlfn.XLOOKUP(order[[#This Row],[order_id]],shipment[order_id],shipment[delivery_date]) -> 45573 | R13: =_xlfn.XLOOKUP(order[[#This Row],[order_id]],shipment[shipment_id],shipment[courier]) -> BlueDart | S13: =order[[#This Row],[selling_price]]-order[[#This Row],[cost_price]]*order[[#This Row],[quantity]]-order[[#This Row],[discount]] -> -91242 | T13: =order[[#This Row],[quantity]]*order[[#This Row],[selling_price]] -> 34680
... A1201: 1053 | B1201: 45605 | C1201: 273 | D1201: =_xlfn.XLOOKUP(order[[#This Row],[customer_id]],customer[customer_id],customer[customer_name]) -> Pooja Nair | E1201: 209 | F1201: 2 | G1201: 1931 | H1201: 1951 | I1201: North | J1201: Delivered | K1201: =_xlfn.XLOOKUP(order[[#This Row],[customer_id]],customer[customer_id],customer[city]) -> Bangalore | L1201: =_xlfn.XLOOKUP(order[[#This Row],[customer_id]],customer[customer_id],customer[state]) -> Karnataka | M1201: =_xlfn.XLOOKUP(order[[#This Row],[product_id]],products!$A$2:$A$11,products!$B$2:$B$11) -> Milton Thermosteel Bottle | N1201: =_xlfn.XLOOKUP(order[[#This Row],[product_id]],products!$A$2:$A$11,products!$C$2:$C$11) -> Home & Kitchen | O1201: =_xlfn.XLOOKUP(order[[#This Row],[product_id]],Table4[product_id],Table4[cost_price]) -> 800 | P1201: =_xlfn.XLOOKUP(order[[#This Row],[order_id]],shipment[order_id],shipment[ship_date]) -> 45414 | Q1201: =_xlfn.XLOOKUP(order[[#This Row],[order_id]],shipment[order_id],shipment[delivery_date]) -> 45415 | R1201: =_xlfn.XLOOKUP(order[[#This Row],[order_id]],shipment[shipment_id],shipment[courier]) -> Ekart | S1201: =order[[#This Row],[selling_price]]-order[[#This Row],[cost_price]]*order[[#This Row],[quantity]]-order[[#This Row],[discount]] -> -1620 | T1201: =order[[#This Row],[quantity]]*order[[#This Row],[selling_price]] -> 3862

Sheet customers
A1: customer_id | B1: customer_name | C1: city | D1: state | E1: signup_date
A2: 101 | B2: Manish Yadav | C2: Chennai | D2: Tamil Nadu | E2: 45347
A3: 102 | B3: Aarav Sharma | C3: Delhi | D3: Delhi | E3: 44624
A4: 103 | B4: Vikram Singh | C4: Delhi | D4: Delhi | E4: 44673
A5: 104 | B5: Aarav Sharma | C5: Bangalore | D5: Karnataka | E5: 45142
A6: 105 | B6: Vikram Singh | C6: Pune | D6: Maharashtra | E6: 45253
A7: 106 | B7: Pooja Nair | C7: Pune | D7: Maharashtra | E7: 45353
A8: 107 | B8: Pooja Nair | C8: Pune | D8: Maharashtra | E8: 44652
A9: 108 | B9: Arjun Nair | C9: Ahmedabad | D9: Gujarat | E9: 44835
A10: 109 | B10: Sneha Iyer | C10: Hyderabad | D10: Telangana | E10: 45003
A11: 110 | B11: Rahul Mehta | C11: Delhi | D11: Delhi | E11: 45129
A12: 111 | B12: Ishita Bose | C12: Ahmedabad | D12: Gujarat | E12: 45167
A13: 112 | B13: Siddharth Jain | C13: Mumbai | D13: Maharashtra | E13: 45032
... A201: 300 | B201: Pooja Nair | C201: Bangalore | D201: Karnataka | E201: 44914

Sheet products
A1: product_id | B1: product_name | C1: category | D1: cost_price
A2: 201 | B2: iPhone 13 | C2: Electronics | D2: 52000
A3: 202 | B3: Samsung Galaxy S21 | C3: Electronics | D3: 45000
A4: 203 | B4: Nike Air Max Shoes | C4: Fashion | D4: 4000
A5: 204 | B5: Levi's Slim Fit Jeans | C5: Fashion | D5: 1800
A6: 205 | B6: Prestige Pressure Cooker 5L | C6: Home & Kitchen | D6: 1200
A7: 206 | B7: Philips Air Fryer | C7: Home & Kitchen | D7: 7000
A8: 207 | B8: Sony WH-1000XM4 Headphones | C8: Electronics | D8: 20000
A9: 208 | B9: Adidas Ultraboost Shoes | C9: Fashion | D9: 9000
A10: 209 | B10: Milton Thermosteel Bottle | C10: Home & Kitchen | D10: 800
A11: 210 | B11: LG 43 Inch Smart TV | C11: Electronics | D11: 30000

Sheet shipments
A1: shipment_id | B1: order_id | C1: ship_date | D1: delivery_date | E1: courier | F1: delivery_status
A2: 1 | B2: 1 | C2: 45598 | D2: 45599 | E2: BlueDart | F2: Delivered
A3: 2 | B3: 2 | C3: 45557 | D3: 45560 | E3: BlueDart | F3: Delayed
A4: 3 | B4: 3 | C4: 45344 | D4: 45349 | E4: BlueDart | F4: Delayed
A5: 4 | B5: 4 | C5: 45657 | D5: 45661 | E5: Delhivery | F5: Delivered
A6: 5 | B6: 5 | C6: 45407 | D6: 45412 | E6: Ekart | F6: Delayed
A7: 6 | B7: 6 | C7: 45609 | D7: 45613 | E7: Ekart | F7: Delayed
A8: 7 | B8: 7 | C8: 45637 | D8: 45647 | E8: BlueDart | F8: Delayed
A9: 8 | B9: 8 | C9: 45489 | D9: 45493 | E9: BlueDart | F9: Delayed
A10: 9 | B10: 9 | C10: 45536 | D10: 45544 | E10: BlueDart | F10: Delayed
A11: 10 | B11: 10 | C11: 45389 | D11: 45394 | E11: DTDC | F11: Delivered
A12: 11 | B12: 11 | C12: 45345 | D12: 45347 | E12: Delhivery | F12: Delayed
A13: 12 | B13: 12 | C13: 45528 | D13: 45531 | E13: Delhivery | F13: Delayed
... A1201: 1200 | B1201: 1200 | C1201: 45630 | D1201: 45633 | E1201: DTDC | F1201: Delivered
